examples/__init__.py
examples/complex.py
examples/options.py
examples/simple.py
socratic/__init__.py
socratic/__version__.py
socratic/dialogue.py
socratic/utils.py
socratic-0.1.1.dist-info/LICENSE.txt
socratic-0.1.1.dist-info/METADATA
socratic-0.1.1.dist-info/WHEEL
socratic-0.1.1.dist-info/top_level.txt
socratic-0.1.1.dist-info/RECORD
