Metadata-Version: 2.1
Name: socratic
Version: 0.1.1
Summary: Socratic - simple question-answer dialog system.
Home-page: https://github.com/dvvolynkin/socratic
Author: Daniil Volynkin
Author-email: foxezzz@gmail.com
License: MIT
Platform: any
Classifier: License :: OSI Approved :: MIT License
Classifier: Natural Language :: English
Classifier: Intended Audience :: Developers
Classifier: Topic :: Software Development :: Libraries
Classifier: Programming Language :: Python
Classifier: Programming Language :: Python :: 3.7
Requires-Python: >=3.7
